forsun/__init__.py
forsun/config.py
forsun/error.py
forsun/extension.py
forsun/forsun.py
forsun/log.py
forsun/plan.py
forsun/status.py
forsun/timer.py
forsun/utils.py
forsun/version.py
forsun/action/__init__.py
forsun/action/action.py
forsun/action/drivers/__init__.py
forsun/action/drivers/beanstalkaction.py
forsun/action/drivers/httpaction.py
forsun/action/drivers/kafkaaction.py
forsun/action/drivers/mysqlaction.py
forsun/action/drivers/rabbitmqaction.py
forsun/action/drivers/redisaction.py
forsun/action/drivers/shellaction.py
forsun/action/drivers/thrifaction.py
forsun/action/drivers/thriftaction.py
forsun/action/drivers/grpcaction/__init__.py
forsun/clients/__init__.py
forsun/clients/client/Forsun.py
forsun/clients/client/__init__.py
forsun/clients/client/constants.py
forsun/clients/client/ttypes.py
forsun/scripts/__init__.py
forsun/scripts/forsun.py
forsun/scripts/forsund.py
forsun/servers/__init__.py
forsun/servers/handler.py
forsun/servers/http.py
forsun/servers/server.py
forsun/servers/processor/Forsun.py
forsun/servers/processor/__init__.py
forsun/servers/processor/constants.py
forsun/servers/processor/ttypes.py
forsun/store/__init__.py
forsun/store/store.py
forsun/store/drivers/__init__.py
forsun/store/drivers/mem.py
forsun/store/drivers/redis.py
gen-py/__init__.py
gen-py/forsun/Forsun.py
gen-py/forsun/__init__.py
gen-py/forsun/constants.py
gen-py/forsun/ttypes.py
forsun-0.1.3.dist-info/LICENSE
forsun-0.1.3.dist-info/METADATA
forsun-0.1.3.dist-info/WHEEL
forsun-0.1.3.dist-info/entry_points.txt
forsun-0.1.3.dist-info/top_level.txt
forsun-0.1.3.dist-info/RECORD
