Metadata-Version: 2.1
Name: forsun
Version: 0.1.3
Summary: High-performance high-precision timing scheduling service
Home-page: https://github.com/snower/forsun
Author: snower
Author-email: sujian199@gmail.com
License: MIT
Platform: UNKNOWN
Requires-Dist: tornado (<=5.1,>=5.0)
Requires-Dist: thrift (==0.11.0)
Requires-Dist: torthrift (>=0.2.4)
Requires-Dist: tornadis (<=0.8.1,>=0.8.0)
Requires-Dist: greenlet (>=0.4.2)
Requires-Dist: msgpack (>=0.5.1)
Requires-Dist: pytz (>=2017.3)
Requires-Dist: tzlocal (>=1.5.1)
Requires-Dist: configparser (>=3.5.0)
Requires-Dist: psutil (>=5.4.7)
Provides-Extra: beanstalk
Requires-Dist: beanstalkt (>=0.7.0) ; extra == 'beanstalk'
Provides-Extra: mysql
Requires-Dist: tormysql (>=0.3.7) ; extra == 'mysql'
